qtoggleserver/eq3bt/__init__.py
qtoggleserver/eq3bt/eq3btthermostat.py
qtoggleserver/eq3bt/exceptions.py
qtoggleserver/eq3bt/ports.py
qtoggleserver_eq3bt-1.6.0.dist-info/licenses/LICENSE.txt
qtoggleserver_eq3bt-1.6.0.dist-info/METADATA
qtoggleserver_eq3bt-1.6.0.dist-info/WHEEL
qtoggleserver_eq3bt-1.6.0.dist-info/top_level.txt
qtoggleserver_eq3bt-1.6.0.dist-info/RECORD
