Metadata-Version: 2.4
Name: qtoggleserver-eq3bt
Version: 1.6.0
Summary: Eqiva eQ-3 bluetooth thermostat support for qToggleServer
Author-email: Calin Crisan <ccrisan@gmail.com>
License: Apache 2.0
Requires-Python: >=3.11
License-File: LICENSE.txt
Dynamic: license-file
